README.txt
setup.py
ext/AnyWrapper.py
ext/AnyWrapperMsgGenerator.py
ext/ComboLeg.py
ext/Contract.py
ext/ContractDetails.py
ext/EClientErrors.py
ext/EClientSocket.py
ext/EReader.py
ext/EWrapper.py
ext/EWrapperMsgGenerator.py
ext/Execution.py
ext/ExecutionFilter.py
ext/Order.py
ext/OrderState.py
ext/ScannerSubscription.py
ext/TagValue.py
ext/TickType.py
ext/UnderComp.py
ext/Util.py
ext/__init__.py
ib.egg-info/PKG-INFO
ib.egg-info/SOURCES.txt
ib.egg-info/dependency_links.txt
ib.egg-info/top_level.txt
lib/__init__.py
lib/logger.py
lib/overloading.py
opt/__init__.py
opt/connection.py
opt/dispatcher.py
opt/message.py
opt/messagetools.py
opt/receiver.py
opt/sender.py
sym/__init__.py