Metadata-Version: 1.0
Name: ib
Version: 0.8.0
Summary: bPy is a third-party implementation of the API used for accessing the Interactive Brokers on-line trading system. IbPy implements functionality that the Python programmer can use to connect to IB, request stock ticker data, submit orders for stocks and futures, and more.
Home-page: UNKNOWN
Author: Colin.Alexander
Author-email: colin.1.alexander@gmail.com
License: MIT
Platform: UNKNOWN
